babyyoda/__init__.py
babyyoda/_version.py
babyyoda/analysisobject.py
babyyoda/axis.py
babyyoda/counter.py
babyyoda/histo1d.py
babyyoda/histo2d.py
babyyoda/plot.py
babyyoda/read.py
babyyoda/test.py
babyyoda/util.py
babyyoda/write.py
babyyoda/cli/main.py
babyyoda/grogu/__init__.py
babyyoda/grogu/analysis_object.py
babyyoda/grogu/counter_v2.py
babyyoda/grogu/counter_v3.py
babyyoda/grogu/estimate0d_v3.py
babyyoda/grogu/estimate1d_v3.py
babyyoda/grogu/estimate2d_v3.py
babyyoda/grogu/histo1d_v2.py
babyyoda/grogu/histo1d_v3.py
babyyoda/grogu/histo2d_v2.py
babyyoda/grogu/histo2d_v3.py
babyyoda/grogu/read.py
babyyoda/grogu/write.py
babyyoda/yoda/__init__.py
babyyoda/yoda/counter.py
babyyoda/yoda/histo1d.py
babyyoda/yoda/histo2d.py
babyyoda/yoda/read.py
babyyoda/yoda/write.py
babyyoda-0.0.8.dist-info/METADATA
babyyoda-0.0.8.dist-info/WHEEL
babyyoda-0.0.8.dist-info/entry_points.txt
babyyoda-0.0.8.dist-info/licenses/LICENSE
babyyoda-0.0.8.dist-info/RECORD
