Metadata-Version: 2.3
Name: babyyoda
Version: 0.0.8
Project-URL: Documentation, https://github.com/APN-Pucky/babyyoda#readme
Project-URL: Issues, https://github.com/APN-Pucky/babyyoda/issues
Project-URL: Source, https://github.com/APN-Pucky/babyyoda/
Author-email: Alexander Puck Neuwirth <alexander@neuwirth-informatik.de>
Classifier: Development Status :: 4 - Beta
Classifier: Intended Audience :: Developers
Classifier: Intended Audience :: Science/Research
Classifier: License :: OSI Approved :: BSD License
Classifier: Programming Language :: Python
Classifier: Programming Language :: Python :: 3.9
Classifier: Programming Language :: Python :: 3.10
Classifier: Programming Language :: Python :: 3.11
Classifier: Programming Language :: Python :: 3.12
Classifier: Programming Language :: Python :: 3.13
Classifier: Programming Language :: Python :: Implementation :: CPython
Classifier: Programming Language :: Python :: Implementation :: PyPy
Classifier: Topic :: Scientific/Engineering
Requires-Python: >=3.9
Requires-Dist: mplhep>=0.3.55
Requires-Dist: numpy
Requires-Dist: smplr
Requires-Dist: uhi>=1.0.0
Provides-Extra: develop
Requires-Dist: boost-histogram; extra == 'develop'
Requires-Dist: hist; extra == 'develop'
Requires-Dist: histoprint; extra == 'develop'
Requires-Dist: mplhep; extra == 'develop'
Requires-Dist: notebook; extra == 'develop'
Requires-Dist: pre-commit; extra == 'develop'
Requires-Dist: pydocstyle; extra == 'develop'
Requires-Dist: pytest-cov>=2.5.1; extra == 'develop'
Requires-Dist: pytest>=6.0; extra == 'develop'
Requires-Dist: ruff; extra == 'develop'
Requires-Dist: tbump>=6.7.0; extra == 'develop'
Provides-Extra: docs
Requires-Dist: sphinx; extra == 'docs'
Provides-Extra: lint
Requires-Dist: ruff; extra == 'lint'
Provides-Extra: test
Requires-Dist: boost-histogram; extra == 'test'
Requires-Dist: hist; extra == 'test'
Requires-Dist: histoprint; extra == 'test'
Requires-Dist: mplhep; extra == 'test'
Requires-Dist: pydocstyle; extra == 'test'
Requires-Dist: pytest-cov>=2.5.1; extra == 'test'
Requires-Dist: pytest>=6.0; extra == 'test'
